multiplayer_session_recorder/__init__.py
multiplayer_session_recorder/constants/__init__.py
multiplayer_session_recorder/exporter/__init__.py
multiplayer_session_recorder/exporter/helpers.py
multiplayer_session_recorder/exporter/log_wrapper.py
multiplayer_session_recorder/exporter/span_wrapper.py
multiplayer_session_recorder/exporter/grpc/__init__.py
multiplayer_session_recorder/exporter/grpc/log_exporter.py
multiplayer_session_recorder/exporter/grpc/trace_exporter.py
multiplayer_session_recorder/exporter/http/__init__.py
multiplayer_session_recorder/exporter/http/log_exporter.py
multiplayer_session_recorder/exporter/http/trace_exporter.py
multiplayer_session_recorder/middleware/__init__.py
multiplayer_session_recorder/middleware/django_http_payload_recorder.py
multiplayer_session_recorder/middleware/flask_http_payload_recorder.py
multiplayer_session_recorder/sdk/__init__.py
multiplayer_session_recorder/sdk/capture_exception.py
multiplayer_session_recorder/sdk/mask.py
multiplayer_session_recorder/sdk/session_id_generator.py
multiplayer_session_recorder/sdk/set_attribute.py
multiplayer_session_recorder/sdk/truncate.py
multiplayer_session_recorder/services/api_service.py
multiplayer_session_recorder/session_recorder/__init__.py
multiplayer_session_recorder/trace/id_generator.py
multiplayer_session_recorder/trace/sampler.py
multiplayer_session_recorder/types/middleware_config.py
multiplayer_session_recorder/types/session_recorder_config.py
multiplayer_session_recorder/types/session_type.py
multiplayer_session_recorder-1.0.6.dist-info/METADATA
multiplayer_session_recorder-1.0.6.dist-info/WHEEL
multiplayer_session_recorder-1.0.6.dist-info/licenses/LICENSE
multiplayer_session_recorder-1.0.6.dist-info/RECORD
